[
  {
    "sorteo": "4671",
    "fecha": "24-03-2023",
    "img": "https://i.postimg.cc/3JcGxSpw/medellin4671.webp",
    "imgAlt": "Seco Medellín 4671"
  },
  {
    "sorteo": "4670",
    "fecha": "17-03-2023",
    "img": "https://i.postimg.cc/fWSt7pqn/medellin4670.webp",
    "imgAlt": "Seco Medellín 4670"
  },
  {
    "sorteo": "4669",
    "fecha": "10-03-2023",
    "img": "https://i.postimg.cc/7YXp545N/medellin4669.webp",
    "imgAlt": "Seco Medellín 4669"
  },
  {
    "sorteo": "4668",
    "fecha": "03-03-2023",
    "img": "https://i.postimg.cc/br94Hc3p/medellin4668.webp",
    "imgAlt": "Seco Medellín 4668"
  },
  {
    "sorteo": "4667",
    "fecha": "24-02-2023",
    "img": "https://i.postimg.cc/Twmz1Wby/medellin4667.webp",
    "imgAlt": "Seco Medellín 4667"
  },
  {
    "sorteo": "4666",
    "fecha": "17-02-2023",
    "img": "https://i.postimg.cc/FFbtQ3m8/medellin4666.webp",
    "imgAlt": "Seco Medellín 4666"
  },
  {
    "sorteo": "4665",
    "fecha": "10-02-2023",
    "img": "https://i.postimg.cc/0N6Rg420/medellin4665.webp",
    "imgAlt": "Seco Medellín 4665"
  },
  {
    "sorteo": "4664",
    "fecha": "03-02-2023",
    "img": "https://i.postimg.cc/JzzCxnfg/medellin4664.webp",
    "imgAlt": "Seco Medellín 4664"
  },
  {
    "sorteo": "4663",
    "fecha": "27-01-2023",
    "img": "https://i.postimg.cc/T3NM4xGP/medellin4663.webp",
    "imgAlt": "Seco Medellín 4663"
  },
  {
    "sorteo": "4662",
    "fecha": "20-01-2023",
    "img": "https://i.postimg.cc/v85yHC7P/medellin4662.jpg",
    "imgAlt": "Seco Medellín 4662"
  },
  {
    "sorteo": "4661",
    "fecha": "13-01-2023",
    "img": "https://i.postimg.cc/xdWr9PXD/medellin4661.webp",
    "imgAlt": "Seco Medellín 4661"
  },
  {
    "sorteo": "4660",
    "fecha": "06-01-2023",
    "img": "https://i.postimg.cc/SNrpc8vC/medellin4660.webp",
    "imgAlt": "Seco Medellín 4660"
  }
]